ccflow/__init__.py
ccflow/arrow.py
ccflow/base.py
ccflow/callable.py
ccflow/compose.py
ccflow/context.py
ccflow/enums.py
ccflow/global_state.py
ccflow/object_config.py
ccflow/publisher.py
ccflow/py.typed
ccflow/serialization.py
ccflow/validators.py
ccflow/evaluators/__init__.py
ccflow/evaluators/common.py
ccflow/examples/__init__.py
ccflow/examples/example.parquet
ccflow/examples/etl/__init__.py
ccflow/examples/etl/__main__.py
ccflow/examples/etl/explain.py
ccflow/examples/etl/models.py
ccflow/examples/etl/config/__init__.py
ccflow/examples/etl/config/base.yaml
ccflow/examples/etl/config/extract/rest.yaml
ccflow/examples/etl/config/load/db.yaml
ccflow/examples/etl/config/transform/links.yaml
ccflow/examples/tpch/__init__.py
ccflow/examples/tpch/base.py
ccflow/examples/tpch/data_generators.py
ccflow/examples/tpch/query.py
ccflow/examples/tpch/config/conf.yaml
ccflow/examples/tpch/queries/LICENSE.md
ccflow/examples/tpch/queries/README.md
ccflow/examples/tpch/queries/__init__.py
ccflow/examples/tpch/queries/q1.py
ccflow/examples/tpch/queries/q10.py
ccflow/examples/tpch/queries/q11.py
ccflow/examples/tpch/queries/q12.py
ccflow/examples/tpch/queries/q13.py
ccflow/examples/tpch/queries/q14.py
ccflow/examples/tpch/queries/q15.py
ccflow/examples/tpch/queries/q16.py
ccflow/examples/tpch/queries/q17.py
ccflow/examples/tpch/queries/q18.py
ccflow/examples/tpch/queries/q19.py
ccflow/examples/tpch/queries/q2.py
ccflow/examples/tpch/queries/q20.py
ccflow/examples/tpch/queries/q21.py
ccflow/examples/tpch/queries/q22.py
ccflow/examples/tpch/queries/q3.py
ccflow/examples/tpch/queries/q4.py
ccflow/examples/tpch/queries/q5.py
ccflow/examples/tpch/queries/q6.py
ccflow/examples/tpch/queries/q7.py
ccflow/examples/tpch/queries/q8.py
ccflow/examples/tpch/queries/q9.py
ccflow/exttypes/__init__.py
ccflow/exttypes/arrow.py
ccflow/exttypes/exprtk.py
ccflow/exttypes/frequency.py
ccflow/exttypes/jinja.py
ccflow/exttypes/narwhals.py
ccflow/exttypes/polars.py
ccflow/exttypes/pyobjectpath.py
ccflow-0.8.0.dist-info/METADATA
ccflow-0.8.0.dist-info/WHEEL
ccflow-0.8.0.dist-info/licenses/LICENSE
ccflow-0.8.0.dist-info/RECORD
