Metadata-Version: 2.4
Name: ccflow
Version: 0.8.0
Summary: ccflow is a collection of tools for workflow configuration, orchestration, and dependency injection
Project-URL: Repository, https://github.com/Point72/ccflow
Project-URL: Homepage, https://github.com/Point72/ccflow
Author-email: "Point72, L.P." <OpenSource@point72.com>
License: Apache-2.0
License-File: LICENSE
Keywords: configuration,dag,flow,hydra,pydantic
Classifier: Development Status :: 4 - Beta
Classifier: License :: OSI Approved :: Apache Software License
Classifier: Programming Language :: Python
Classifier: Programming Language :: Python :: 3
Classifier: Programming Language :: Python :: 3.10
Classifier: Programming Language :: Python :: 3.11
Classifier: Programming Language :: Python :: 3.12
Classifier: Programming Language :: Python :: 3.13
Classifier: Programming Language :: Python :: 3.14
Classifier: Programming Language :: Python :: Implementation :: CPython
Classifier: Programming Language :: Python :: Implementation :: PyPy
Requires-Python: >=3.10
Requires-Dist: cloudpathlib
Requires-Dist: cloudpickle
Requires-Dist: dask
Requires-Dist: deprecated
Requires-Dist: hydra-core
Requires-Dist: ipython
Requires-Dist: jinja2
Requires-Dist: narwhals
Requires-Dist: numpy<3
Requires-Dist: orjson
Requires-Dist: pandas
Requires-Dist: pyarrow
Requires-Dist: pydantic<3,>=2.6
Requires-Dist: smart-open
Requires-Dist: tenacity
Provides-Extra: develop
Requires-Dist: beautifulsoup4; extra == 'develop'
Requires-Dist: build; extra == 'develop'
Requires-Dist: bump-my-version; extra == 'develop'
Requires-Dist: cexprtk; extra == 'develop'
Requires-Dist: check-manifest; extra == 'develop'
Requires-Dist: codespell<2.5,>=2.4; extra == 'develop'
Requires-Dist: csp<1,>=0.8.0; extra == 'develop'
Requires-Dist: duckdb; extra == 'develop'
Requires-Dist: hatchling; extra == 'develop'
Requires-Dist: httpx; extra == 'develop'
Requires-Dist: mdformat-tables>=1; extra == 'develop'
Requires-Dist: mdformat<1.1,>=0.7.22; extra == 'develop'
Requires-Dist: pandas; extra == 'develop'
Requires-Dist: plotly; extra == 'develop'
Requires-Dist: polars; extra == 'develop'
Requires-Dist: pytest; extra == 'develop'
Requires-Dist: pytest-asyncio; extra == 'develop'
Requires-Dist: pytest-cov; extra == 'develop'
Requires-Dist: pytest-mock; extra == 'develop'
Requires-Dist: pytest-sugar; extra == 'develop'
Requires-Dist: ray; extra == 'develop'
Requires-Dist: ruff<0.15,>=0.9; extra == 'develop'
Requires-Dist: scipy; extra == 'develop'
Requires-Dist: toml; extra == 'develop'
Requires-Dist: twine; extra == 'develop'
Requires-Dist: uv; extra == 'develop'
Requires-Dist: wheel; extra == 'develop'
Requires-Dist: xarray; extra == 'develop'
Provides-Extra: full
Requires-Dist: cexprtk; extra == 'full'
Requires-Dist: duckdb; extra == 'full'
Requires-Dist: pandas; extra == 'full'
Requires-Dist: plotly; extra == 'full'
Requires-Dist: polars; extra == 'full'
Requires-Dist: ray; extra == 'full'
Requires-Dist: scipy; extra == 'full'
Requires-Dist: xarray; extra == 'full'
Provides-Extra: test
Requires-Dist: beautifulsoup4; extra == 'test'
Requires-Dist: httpx; extra == 'test'
Requires-Dist: pytest; extra == 'test'
Requires-Dist: pytest-asyncio; extra == 'test'
Requires-Dist: pytest-cov; extra == 'test'
Requires-Dist: pytest-sugar; extra == 'test'
